clause_analysis/__init__.py
clause_analysis/active_phrase_extractor.py
clause_analysis/clause_analyzer.py
clause_analysis/conjunctions_cleaner.py
clause_analysis/passive_phrase_extractor.py
clause_analysis/passive_phrase_extractor.py.py
clause_analysis/passive_tense_classifier.py
clause_analysis/subject_adder.py
clause_analysis/tense_analyzer.py
tests/__init__.py
tests/test_clause_analyzer.py
tests/test_passive_tense_classifier.py
tests/test_tense_analyzer.py
clause_analysis-0.3.6.dist-info/METADATA
clause_analysis-0.3.6.dist-info/WHEEL
clause_analysis-0.3.6.dist-info/entry_points.txt
clause_analysis-0.3.6.dist-info/top_level.txt
clause_analysis-0.3.6.dist-info/RECORD
