Metadata-Version: 2.1
Name: clause_analysis
Version: 0.3.6
Summary: A library to analyze clauses and classify tenses.
Home-page: https://github.com/Kritpofrankss/clause_analysis
Author: Kritpofrankss
Author-email: Krit.poshakrishna@gmail.com
Classifier: Programming Language :: Python :: 3
Classifier: License :: OSI Approved :: MIT License
Classifier: Operating System :: OS Independent
Requires-Python: >=3.6
Requires-Dist: nltk
Requires-Dist: spacy
Requires-Dist: requests
